[
    {
        "id":1,
        "title":"yuki.me - frontend - portfolio",
        "labels":["JS","HTML","CSS"],
        "youtube":"https://www.youtube.com/watch?v=9L60q0fQHu8",
        "website":"https://yukime.vercel.app/",
        "github":"https://github.com/YuKissGit/yuki.me--frontend",
        "image":"./public/static/image/p1-frontend.png"
    },
    {
        "id":2,
        "title":"yuki.me - backend - comment",
        "labels":["Vanilla NodeJS"],
        "youtube":"https://www.youtube.com/watch?v=9L60q0fQHu8",
        "website":"https://yukime.vercel.app/",
        "github":"https://github.com/YuKissGit/yuki.me--backend",
        "image":"./public/static/image/p2-backend.png"
    }

]